{
  "id": "https://w3id.org/openeduhub/vocabs/keyword_catalogue/verkehrserziehung_systematik/transport",
  "type": "Concept",
  "followers": "https://test.skohub.io/followers?subject=w3id.org%2Fopeneduhub%2Fvocabs%2Fkeyword_catalogue%2Fverkehrserziehung_systematik%2Ftransport",
  "inbox": "https://test.skohub.io/inbox?target=w3id.org%2Fopeneduhub%2Fvocabs%2Fkeyword_catalogue%2Fverkehrserziehung_systematik%2Ftransport",
  "prefLabel": {
    "de": "Transport"
  },
  "narrower": [
    {
      "id": "https://w3id.org/openeduhub/vocabs/keyword_catalogue/verkehrserziehung_systematik/deutsche_bahn_ag",
      "prefLabel": {
        "de": "Deutsche Bahn AG"
      }
    },
    {
      "id": "https://w3id.org/openeduhub/vocabs/keyword_catalogue/verkehrserziehung_systematik/eisenbahn",
      "prefLabel": {
        "de": "Eisenbahn"
      }
    },
    {
      "id": "https://w3id.org/openeduhub/vocabs/keyword_catalogue/verkehrserziehung_systematik/eisenbahn_geschichte",
      "prefLabel": {
        "de": "Eisenbahn (Geschichte)"
      }
    },
    {
      "id": "https://w3id.org/openeduhub/vocabs/keyword_catalogue/verkehrserziehung_systematik/fracht",
      "prefLabel": {
        "de": "Fracht"
      }
    },
    {
      "id": "https://w3id.org/openeduhub/vocabs/keyword_catalogue/verkehrserziehung_systematik/gefahrguttransport",
      "prefLabel": {
        "de": "Gefahrguttransport"
      }
    },
    {
      "id": "https://w3id.org/openeduhub/vocabs/keyword_catalogue/verkehrserziehung_systematik/güterverkehr",
      "prefLabel": {
        "de": "Güterverkehr"
      }
    },
    {
      "id": "https://w3id.org/openeduhub/vocabs/keyword_catalogue/verkehrserziehung_systematik/luftfahrt",
      "prefLabel": {
        "de": "Luftfahrt"
      }
    },
    {
      "id": "https://w3id.org/openeduhub/vocabs/keyword_catalogue/verkehrserziehung_systematik/straßenverkehr",
      "prefLabel": {
        "de": "Straßenverkehr"
      }
    },
    {
      "id": "https://w3id.org/openeduhub/vocabs/keyword_catalogue/verkehrserziehung_systematik/öffentlicher_nahverkehr",
      "prefLabel": {
        "de": "Öffentlicher Nahverkehr"
      }
    }
  ],
  "broader": {
    "id": "https://w3id.org/openeduhub/vocabs/keyword_catalogue/verkehrserziehung_systematik/verkehr",
    "prefLabel": {
      "de": "Verkehr"
    }
  },
  "inScheme": {
    "id": "https://w3id.org/openeduhub/vocabs/keyword_catalogue/verkehrserziehung_systematik/",
    "title": {
      "de": "verkehrserziehung_systematik"
    }
  },
  "@context": {
    "id": "@id",
    "type": "@type",
    "@vocab": "http://www.w3.org/2004/02/skos/core#",
    "xsd": "http://www.w3.org/2001/XMLSchema#",
    "dct": "http://purl.org/dc/terms/",
    "schema": "http://schema.org/",
    "vann": "http://purl.org/vocab/vann/",
    "title": {
      "@id": "dct:title",
      "@container": "@language"
    },
    "description": {
      "@id": "dct:description",
      "@container": "@language"
    },
    "issued": {
      "@id": "dct:issued",
      "@type": "xsd:date"
    },
    "created": {
      "@id": "dct:created",
      "@type": "xsd:date"
    },
    "modified": {
      "@id": "dct:modified",
      "@type": "xsd:date"
    },
    "creator": "dct:creator",
    "publisher": "dct:publisher",
    "preferredNamespacePrefix": "vann:preferredNamespacePrefix",
    "preferredNamespaceUri": "vann:preferredNamespaceUri",
    "isBasedOn": "schema:isBasedOn",
    "source": "dct:source",
    "prefLabel": {
      "@container": "@language"
    },
    "definition": {
      "@container": "@language"
    },
    "scopeNote": {
      "@container": "@language"
    },
    "note": {
      "@container": "@language"
    },
    "notation": {
      "@container": "@set"
    },
    "narrower": {
      "@container": "@set"
    },
    "narrowerTransitive": {
      "@container": "@set"
    },
    "broaderTransitive": {
      "@container": "@set"
    }
  }
}